<?xml version="1.0" encoding="UTF-8"?>
<objects serializationModel="Studio.02.02.00">
	<object class="Event" id="{7cdee043-db77-4a40-9d4a-dc8b837b3589}">
		<property name="name">
			<value>int_bassdeep</value>
		</property>
		<property name="outputFormat">
			<value>2</value>
		</property>
		<relationship name="folder">
			<destination>{6090ca55-c6cc-4d40-85ac-3ba49d678456}</destination>
		</relationship>
		<relationship name="mixer">
			<destination>{72a437c8-21d0-4f39-b9d6-748da423eabe}</destination>
		</relationship>
		<relationship name="masterTrack">
			<destination>{6ff60b7f-3b95-472e-baa6-2e5cb485e7bd}</destination>
		</relationship>
		<relationship name="mixerInput">
			<destination>{7507e0cd-8b8e-4283-81e6-612c84dffbb7}</destination>
		</relationship>
		<relationship name="automatableProperties">
			<destination>{3e0e7dc8-3f0e-40c1-8807-35c8a43f89fc}</destination>
		</relationship>
		<relationship name="markerTracks">
			<destination>{9c663957-14ba-4ab9-825c-7ef60f3a8ea4}</destination>
		</relationship>
		<relationship name="groupTracks">
			<destination>{20d59828-325f-41ab-8c7c-005e00bd5c06}</destination>
		</relationship>
		<relationship name="timeline">
			<destination>{aba1f04a-6a47-4400-b109-770b26c1fcaa}</destination>
		</relationship>
		<relationship name="parameters">
			<destination>{f11d7d32-e28c-4a3f-bc7b-487a4b84e391}</destination>
			<destination>{c3fb84c2-88e0-4e6b-83e1-9f6f0990da5f}</destination>
		</relationship>
		<relationship name="banks">
			<destination>{87f0ba3f-babd-4d67-8423-0dc72d27bba9}</destination>
		</relationship>
	</object>
	<object class="EventMixer" id="{72a437c8-21d0-4f39-b9d6-748da423eabe}">
		<relationship name="masterBus">
			<destination>{6d38d4b3-779d-4a9f-aad2-b7e67c2c74a0}</destination>
		</relationship>
	</object>
	<object class="MasterTrack" id="{6ff60b7f-3b95-472e-baa6-2e5cb485e7bd}">
		<relationship name="mixerGroup">
			<destination>{6d38d4b3-779d-4a9f-aad2-b7e67c2c74a0}</destination>
		</relationship>
	</object>
	<object class="MixerInput" id="{7507e0cd-8b8e-4283-81e6-612c84dffbb7}">
		<relationship name="effectChain">
			<destination>{65cd3cea-47a4-4b8a-9c99-731e717c522f}</destination>
		</relationship>
		<relationship name="panner">
			<destination>{46007a48-6bac-4dc3-97dd-9e999c4172a8}</destination>
		</relationship>
		<relationship name="output">
			<destination>{625e1164-2cc0-409d-b84a-0a9b9283c3fc}</destination>
		</relationship>
	</object>
	<object class="EventAutomatableProperties" id="{3e0e7dc8-3f0e-40c1-8807-35c8a43f89fc}">
		<property name="isPersistent">
			<value>true</value>
		</property>
		<property name="maxVoices">
			<value>8</value>
		</property>
		<property name="voiceStealing">
			<value>4</value>
		</property>
		<property name="maximumDistance">
			<value>1000</value>
		</property>
	</object>
	<object class="MarkerTrack" id="{9c663957-14ba-4ab9-825c-7ef60f3a8ea4}" />
	<object class="GroupTrack" id="{20d59828-325f-41ab-8c7c-005e00bd5c06}">
		<relationship name="modules">
			<destination>{5fcb8cc4-41d7-4522-a4f9-e2b2523c71b7}</destination>
		</relationship>
		<relationship name="mixerGroup">
			<destination>{193b6ce0-1119-48b3-bbc2-94727540b387}</destination>
		</relationship>
	</object>
	<object class="Timeline" id="{aba1f04a-6a47-4400-b109-770b26c1fcaa}">
		<relationship name="modules">
			<destination>{5fcb8cc4-41d7-4522-a4f9-e2b2523c71b7}</destination>
		</relationship>
		<relationship name="markers">
			<destination>{142c336b-d115-43ba-8282-779b7c809761}</destination>
		</relationship>
	</object>
	<object class="ParameterProxy" id="{f11d7d32-e28c-4a3f-bc7b-487a4b84e391}">
		<relationship name="preset">
			<destination>{3bd56dbc-526a-40ca-9c42-2fd6e978e3ec}</destination>
		</relationship>
	</object>
	<object class="ParameterProxy" id="{c3fb84c2-88e0-4e6b-83e1-9f6f0990da5f}">
		<relationship name="preset">
			<destination>{2da992d1-c53a-49d7-8897-4cfc91bad01a}</destination>
		</relationship>
	</object>
	<object class="EventMixerMaster" id="{6d38d4b3-779d-4a9f-aad2-b7e67c2c74a0}">
		<relationship name="effectChain">
			<destination>{60178f38-d0a5-4282-9573-f5b5211f8d96}</destination>
		</relationship>
		<relationship name="panner">
			<destination>{4d05a067-a473-4a51-b84d-7fb8a036419e}</destination>
		</relationship>
		<relationship name="mixer">
			<destination>{72a437c8-21d0-4f39-b9d6-748da423eabe}</destination>
		</relationship>
	</object>
	<object class="MixerBusEffectChain" id="{65cd3cea-47a4-4b8a-9c99-731e717c522f}">
		<relationship name="effects">
			<destination>{37782470-63dd-4386-86c6-49f58dc41735}</destination>
		</relationship>
	</object>
	<object class="MixerBusPanner" id="{46007a48-6bac-4dc3-97dd-9e999c4172a8}" />
	<object class="SingleSound" id="{5fcb8cc4-41d7-4522-a4f9-e2b2523c71b7}">
		<property name="isAsync">
			<value>true</value>
		</property>
		<property name="isCutoff">
			<value>true</value>
		</property>
		<property name="length">
			<value>10.769229166666667</value>
		</property>
		<property name="looping">
			<value>true</value>
		</property>
		<relationship name="automators">
			<destination>{7f02b9ab-3c9e-454b-bfbb-68aadc916c73}</destination>
		</relationship>
		<relationship name="modulators">
			<destination>{742eb37c-e563-406c-8e4a-154a3d06f5ad}</destination>
		</relationship>
		<relationship name="audioFile">
			<destination>{25d207c6-c1c4-4a55-a4a5-21ded8d3e749}</destination>
		</relationship>
	</object>
	<object class="EventMixerGroup" id="{193b6ce0-1119-48b3-bbc2-94727540b387}">
		<property name="name">
			<value>Audio 1</value>
		</property>
		<relationship name="effectChain">
			<destination>{d0766d3c-fc4e-4dc1-95d5-e4df5ce69840}</destination>
		</relationship>
		<relationship name="panner">
			<destination>{46f3d05a-e7c5-4677-a438-beec482eeb31}</destination>
		</relationship>
		<relationship name="output">
			<destination>{6d38d4b3-779d-4a9f-aad2-b7e67c2c74a0}</destination>
		</relationship>
	</object>
	<object class="LoopRegion" id="{142c336b-d115-43ba-8282-779b7c809761}">
		<property name="position">
			<value>0</value>
		</property>
		<property name="length">
			<value>10.769229166666667</value>
		</property>
		<relationship name="timeline">
			<destination>{aba1f04a-6a47-4400-b109-770b26c1fcaa}</destination>
		</relationship>
		<relationship name="markerTrack">
			<destination>{9c663957-14ba-4ab9-825c-7ef60f3a8ea4}</destination>
		</relationship>
	</object>
	<object class="MixerBusEffectChain" id="{60178f38-d0a5-4282-9573-f5b5211f8d96}">
		<relationship name="effects">
			<destination>{2dbedc72-1e6b-4957-9d5d-701c6c3409c3}</destination>
			<destination>{74414b55-6bc7-4c4a-963d-93caeead56cc}</destination>
		</relationship>
	</object>
	<object class="MixerBusPanner" id="{4d05a067-a473-4a51-b84d-7fb8a036419e}" />
	<object class="MixerBusFader" id="{37782470-63dd-4386-86c6-49f58dc41735}" />
	<object class="Automator" id="{7f02b9ab-3c9e-454b-bfbb-68aadc916c73}">
		<property name="nameOfPropertyBeingAutomated">
			<value>pitch</value>
		</property>
		<relationship name="automationCurves">
			<destination>{10ace591-bd60-4f40-933c-7450a3b2d0b6}</destination>
		</relationship>
	</object>
	<object class="RandomizerModulator" id="{742eb37c-e563-406c-8e4a-154a3d06f5ad}">
		<property name="nameOfPropertyBeingModulated">
			<value>startOffset</value>
		</property>
		<property name="amount">
			<value>100</value>
		</property>
	</object>
	<object class="MixerBusEffectChain" id="{d0766d3c-fc4e-4dc1-95d5-e4df5ce69840}">
		<relationship name="effects">
			<destination>{bfa937a0-a5f1-4e8d-9381-46f94a322a53}</destination>
		</relationship>
	</object>
	<object class="MixerBusPanner" id="{46f3d05a-e7c5-4677-a438-beec482eeb31}" />
	<object class="MixerBusFader" id="{2dbedc72-1e6b-4957-9d5d-701c6c3409c3}" />
	<object class="SpatialiserEffect" id="{74414b55-6bc7-4c4a-963d-93caeead56cc}">
		<property name="maximumDistance">
			<value>1000</value>
		</property>
		<property name="extentMode">
			<value>1</value>
		</property>
		<property name="soundSize">
			<value>240</value>
		</property>
		<property name="minimumExtent">
			<value>142</value>
		</property>
		<relationship name="automators">
			<destination>{d00c6d50-2401-4561-85cc-7733b5499e7b}</destination>
		</relationship>
	</object>
	<object class="AutomationCurve" id="{10ace591-bd60-4f40-933c-7450a3b2d0b6}">
		<relationship name="parameter">
			<destination>{2da992d1-c53a-49d7-8897-4cfc91bad01a}</destination>
		</relationship>
		<relationship name="automationPoints">
			<destination>{f418646e-7e8f-460c-9153-7644536855ab}</destination>
			<destination>{11241c72-dd91-4277-b6d1-0a61ebbde9a4}</destination>
		</relationship>
	</object>
	<object class="MixerBusFader" id="{bfa937a0-a5f1-4e8d-9381-46f94a322a53}" />
	<object class="Automator" id="{d00c6d50-2401-4561-85cc-7733b5499e7b}">
		<property name="nameOfPropertyBeingAutomated">
			<value>panBlend</value>
		</property>
		<relationship name="automationCurves">
			<destination>{a48d24b8-0500-4699-b760-36986c49f4aa}</destination>
		</relationship>
	</object>
	<object class="AutomationPoint" id="{f418646e-7e8f-460c-9153-7644536855ab}">
		<property name="position">
			<value>0</value>
		</property>
		<property name="value">
			<value>-24</value>
		</property>
	</object>
	<object class="AutomationPoint" id="{11241c72-dd91-4277-b6d1-0a61ebbde9a4}">
		<property name="position">
			<value>1</value>
		</property>
		<property name="value">
			<value>23.5247536</value>
		</property>
	</object>
	<object class="AutomationCurve" id="{a48d24b8-0500-4699-b760-36986c49f4aa}">
		<relationship name="parameter">
			<destination>{3bd56dbc-526a-40ca-9c42-2fd6e978e3ec}</destination>
		</relationship>
		<relationship name="automationPoints">
			<destination>{aaec4ec1-1df1-46a2-97d5-bab360ac3f20}</destination>
			<destination>{01f8e9d8-ce64-49ee-8ea8-6c3b9489ea49}</destination>
			<destination>{0968b938-b116-4f8a-800e-c1925775fa53}</destination>
		</relationship>
	</object>
	<object class="AutomationPoint" id="{aaec4ec1-1df1-46a2-97d5-bab360ac3f20}">
		<property name="position">
			<value>0</value>
		</property>
		<property name="value">
			<value>0</value>
		</property>
	</object>
	<object class="AutomationPoint" id="{01f8e9d8-ce64-49ee-8ea8-6c3b9489ea49}">
		<property name="position">
			<value>99.011299435028249</value>
		</property>
		<property name="value">
			<value>1</value>
		</property>
	</object>
	<object class="AutomationPoint" id="{0968b938-b116-4f8a-800e-c1925775fa53}">
		<property name="position">
			<value>40.536723163841799</value>
		</property>
		<property name="value">
			<value>1</value>
		</property>
	</object>
</objects>
